{
    "users": [
        {
            "id": "wWHVLyktKnQMq7Y3NKgRXF4DOyn1",
            "email": "mandi@redacademy.com",
            "fullname": "Mandi Wise",
            "bio": "Learn 'em good."
        },
        {
            "id": "lOKG7X97wKOqOurQLN5wZbiqisO2",
            "email": "mackenzie@redacademy.com",
            "fullname": "Mackenzie Kieran",
            "bio": "Thar she blows."
        },
        {
            "id": "AVREZHsQH8cv66sUSAogoO2Vn0s2",
            "email": "edivan@redacademy.com",
            "fullname": "Edivan Henrique",
            "bio": "I like dancing :)"
        }
    ]
}
